rabbitmq_pika_flask/ExchangeParams.py
rabbitmq_pika_flask/ExchangeType.py
rabbitmq_pika_flask/QueueParams.py
rabbitmq_pika_flask/RabbitConsumerMiddleware.py
rabbitmq_pika_flask/RabbitMQ.py
rabbitmq_pika_flask/__init__.py
rabbitmq_pika_flask-1.2.35.dist-info/LICENSE
rabbitmq_pika_flask-1.2.35.dist-info/METADATA
rabbitmq_pika_flask-1.2.35.dist-info/WHEEL
rabbitmq_pika_flask-1.2.35.dist-info/top_level.txt
rabbitmq_pika_flask-1.2.35.dist-info/RECORD
