Metadata-Version: 2.1
Name: rabbitmq-pika-flask
Version: 1.2.35
Summary: Adapter for RabbitMQs pika and flask
Home-page: https://github.com/aylton-almeida/rabbitmq-pika-flask
Download-URL: https://github.com/aylton-almeida/rabbitmq-pika-flask/archive/0.1.tar.gz
Author: Aylton Almeida
Author-email: almeida@aylton.dev
License: MIT
Keywords: FLASK,PIKA,RABBITMQ,MESSAGEQUEUE
Classifier: Development Status :: 3 - Alpha
Classifier: Intended Audience :: Developers
Classifier: Topic :: Software Development :: Build Tools
Classifier: License :: OSI Approved :: MIT License
Classifier: Programming Language :: Python :: 3
Classifier: Programming Language :: Python :: 3.8
Classifier: Programming Language :: Python :: 3.9
Classifier: Programming Language :: Python :: 3.10
License-File: LICENSE
Requires-Dist: Flask >=1.1.1
Requires-Dist: pika >=1.2.0
Requires-Dist: retry >=0.9.2
